flash_attention_softmax_n/__init__.py
flash_attention_softmax_n/analysis/__init__.py
flash_attention_softmax_n/analysis/hooks.py
flash_attention_softmax_n/analysis/io.py
flash_attention_softmax_n/analysis/statistics.py
flash_attention_softmax_n/core/__init__.py
flash_attention_softmax_n/core/flash_attn.py
flash_attention_softmax_n/core/flash_attn_triton.py
flash_attention_softmax_n/core/functional.py
flash_attention_softmax_n/surgery/__init__.py
flash_attention_softmax_n/surgery/attention_softmax_n.py
flash_attention_softmax_n/surgery/surgery_functions/__init__.py
flash_attention_softmax_n/surgery/surgery_functions/_bert.py
flash_attention_softmax_n/surgery/surgery_functions/_xlnet.py
flash_attention_softmax_n/surgery/surgery_functions/utils.py
flash_attention_softmax_n-0.3.2.dist-info/LICENSE
flash_attention_softmax_n-0.3.2.dist-info/METADATA
flash_attention_softmax_n-0.3.2.dist-info/WHEEL
flash_attention_softmax_n-0.3.2.dist-info/top_level.txt
flash_attention_softmax_n-0.3.2.dist-info/RECORD
